{"cityid": "101270101", "date": "201605", "city": "\u6210\u90fd", "cityEn": "chengdu", "maxWendu": "30\uff082016-05-11\uff09", "minWendu": "12\uff082016-05-15\uff09", "avgbWendu": "26", "avgyWendu": "17", "maxAqi": "175", "minAqi": "82", "maxAqiInfo": "\u4e2d\u5ea6\u6c61\u67d3", "maxAqiDate": "05\u670805\u65e5", "maxAqiLevel": "4", "minAqiInfo": "\u7a7a\u6c14\u4f18", "minAqiDate": "05\u670826\u65e5", "minAqiLevel": "1", "data": [{"ymd": "2016-05-01", "bWendu": "29\u2103", "yWendu": "17\u2103", "tianqi": "\u591a\u4e91", "fengxiang": "\u5357\u98ce", "fengli": "\u5fae\u98ce", "aqi": "101", "aqiInfo": "\u8f7b\u5ea6\u6c61\u67d3", "aqiLevel": "3"}, {"ymd": "2016-05-02", "bWendu": "29\u2103", "yWendu": "17\u2103", "tianqi": "\u591a\u4e91", "fengxiang": "\u5357\u98ce", "fengli": "\u5fae\u98ce", "aqi": "110", "aqiInfo": "\u8f7b\u5ea6\u6c61\u67d3", "aqiLevel": "3"}, {"ymd": "2016-05-03", "bWendu": "30\u2103", "yWendu": "18\u2103", "tianqi": "\u591a\u4e91", "fengxiang": "\u5317\u98ce", "fengli": "\u5fae\u98ce", "aqi": "78", "aqiInfo": "\u826f", "aqiLevel": "2"}, {"ymd": "2016-05-04", "bWendu": "30\u2103", "yWendu": "18\u2103", "tianqi": "\u591a\u4e91~\u6674", "fengxiang": "\u65e0\u6301\u7eed\u98ce\u5411", "fengli": "\u5fae\u98ce", "aqi": "102", "aqiInfo": "\u8f7b\u5ea6\u6c61\u67d3", "aqiLevel": "3"}, {"ymd": "2016-05-05", "bWendu": "30\u2103", "yWendu": "21\u2103", "tianqi": "\u5c0f\u96e8", "fengxiang": "\u5357\u98ce", "fengli": "\u5fae\u98ce", "aqi": "175", "aqiInfo": "\u4e2d\u5ea6\u6c61\u67d3", "aqiLevel": "4"}, {"ymd": "2016-05-06", "bWendu": "27\u2103", "yWendu": "19\u2103", "tianqi": "\u4e2d\u96e8", "fengxiang": "\u5317\u98ce", "fengli": "3-4\u7ea7", "aqi": "68", "aqiInfo": "\u826f", "aqiLevel": "2"}, {"ymd": "2016-05-07", "bWendu": "22\u2103", "yWendu": "17\u2103", "tianqi": "\u4e2d\u96e8~\u5c0f\u96e8", "fengxiang": "\u5317\u98ce", "fengli": "\u5fae\u98ce", "aqi": "39", "aqiInfo": "\u4f18", "aqiLevel": "1"}, {"ymd": "2016-05-08", "bWendu": "22\u2103", "yWendu": "15\u2103", "tianqi": "\u591a\u4e91~\u4e2d\u96e8", "fengxiang": "\u5317\u98ce", "fengli": "\u5fae\u98ce", "aqi": "53", "aqiInfo": "\u826f", "aqiLevel": "2"}, {"ymd": "2016-05-09", "bWendu": "29\u2103", "yWendu": "16\u2103", "tianqi": "\u591a\u4e91", "fengxiang": "\u5357\u98ce", "fengli": "\u5fae\u98ce", "aqi": "62", "aqiInfo": "\u826f", "aqiLevel": "2"}, {"ymd": "2016-05-10", "bWendu": "30\u2103", "yWendu": "16\u2103", "tianqi": "\u6674", "fengxiang": "\u5357\u98ce", "fengli": "\u5fae\u98ce", "aqi": "77", "aqiInfo": "\u826f", "aqiLevel": "2"}, {"ymd": "2016-05-11", "bWendu": "30\u2103", "yWendu": "19\u2103", "tianqi": "\u6674", "fengxiang": "\u5357\u98ce", "fengli": "\u5fae\u98ce", "aqi": "111", "aqiInfo": "\u8f7b\u5ea6\u6c61\u67d3", "aqiLevel": "3"}, {"ymd": "2016-05-12", "bWendu": "25\u2103", "yWendu": "16\u2103", "tianqi": "\u4e2d\u96e8~\u5c0f\u96e8", "fengxiang": "\u5317\u98ce", "fengli": "\u5fae\u98ce", "aqi": "118", "aqiInfo": "\u8f7b\u5ea6\u6c61\u67d3", "aqiLevel": "3"}, {"ymd": "2016-05-13", "bWendu": "24\u2103", "yWendu": "16\u2103", "tianqi": "\u5c0f\u96e8", "fengxiang": "\u5317\u98ce", "fengli": "3-4\u7ea7", "aqi": "96", "aqiInfo": "\u826f", "aqiLevel": "2"}, {"ymd": "2016-05-14", "bWendu": "21\u2103", "yWendu": "16\u2103", "tianqi": "\u9635\u96e8", "fengxiang": "\u5317\u98ce", "fengli": "\u5fae\u98ce", "aqi": "43", "aqiInfo": "\u4f18", "aqiLevel": "1"}, {"ymd": "2016-05-15", "bWendu": "25\u2103", "yWendu": "12\u2103", "tianqi": "\u591a\u4e91", "fengxiang": "\u5357\u98ce", "fengli": "\u5fae\u98ce", "aqi": "52", "aqiInfo": "\u826f", "aqiLevel": "2"}, {"ymd": "2016-05-16", "bWendu": "25\u2103", "yWendu": "14\u2103", "tianqi": "\u591a\u4e91~\u9634", "fengxiang": "\u5357\u98ce", "fengli": "\u5fae\u98ce", "aqi": "94", "aqiInfo": "\u826f", "aqiLevel": "2"}, {"ymd": "2016-05-17", "bWendu": "26\u2103", "yWendu": "16\u2103", "tianqi": "\u9634~\u591a\u4e91", "fengxiang": "\u5357\u98ce", "fengli": "\u5fae\u98ce", "aqi": "88", "aqiInfo": "\u826f", "aqiLevel": "2"}, {"ymd": "2016-05-18", "bWendu": "27\u2103", "yWendu": "18\u2103", "tianqi": "\u9634~\u5c0f\u96e8", "fengxiang": "\u5357\u98ce", "fengli": "\u5fae\u98ce", "aqi": "112", "aqiInfo": "\u8f7b\u5ea6\u6c61\u67d3", "aqiLevel": "3"}, {"ymd": "2016-05-19", "bWendu": "26\u2103", "yWendu": "17\u2103", "tianqi": "\u5c0f\u96e8~\u6674", "fengxiang": "\u5357\u98ce", "fengli": "\u5fae\u98ce", "aqi": "109", "aqiInfo": "\u8f7b\u5ea6\u6c61\u67d3", "aqiLevel": "3"}, {"ymd": "2016-05-20", "bWendu": "27\u2103", "yWendu": "18\u2103", "tianqi": "\u591a\u4e91~\u5c0f\u96e8", "fengxiang": "\u5357\u98ce", "fengli": "\u5fae\u98ce", "aqi": "74", "aqiInfo": "\u826f", "aqiLevel": "2"}, {"ymd": "2016-05-21", "bWendu": "25\u2103", "yWendu": "18\u2103", "tianqi": "\u5c0f\u96e8~\u4e2d\u96e8", "fengxiang": "\u5317\u98ce", "fengli": "\u5fae\u98ce", "aqi": "59", "aqiInfo": "\u826f", "aqiLevel": "2"}, {"ymd": "2016-05-22", "bWendu": "20\u2103", "yWendu": "18\u2103", "tianqi": "\u4e2d\u96e8", "fengxiang": "\u5317\u98ce", "fengli": "\u5fae\u98ce", "aqi": "37", "aqiInfo": "\u4f18", "aqiLevel": "1"}, {"ymd": "2016-05-23", "bWendu": "24\u2103", "yWendu": "15\u2103", "tianqi": "\u5c0f\u96e8~\u9634", "fengxiang": "\u5317\u98ce", "fengli": "\u5fae\u98ce", "aqi": "37", "aqiInfo": "\u4f18", "aqiLevel": "1"}, {"ymd": "2016-05-24", "bWendu": "26\u2103", "yWendu": "16\u2103", "tianqi": "\u591a\u4e91~\u9635\u96e8", "fengxiang": "\u5357\u98ce", "fengli": "\u5fae\u98ce", "aqi": "59", "aqiInfo": "\u826f", "aqiLevel": "2"}, {"ymd": "2016-05-25", "bWendu": "22\u2103", "yWendu": "15\u2103", "tianqi": "\u5927\u96e8~\u4e2d\u96e8", "fengxiang": "\u5317\u98ce", "fengli": "3-4\u7ea7", "aqi": "63", "aqiInfo": "\u826f", "aqiLevel": "2"}, {"ymd": "2016-05-26", "bWendu": "22\u2103", "yWendu": "15\u2103", "tianqi": "\u9634", "fengxiang": "\u5317\u98ce", "fengli": "\u5fae\u98ce", "aqi": "33", "aqiInfo": "\u4f18", "aqiLevel": "1"}, {"ymd": "2016-05-27", "bWendu": "23\u2103", "yWendu": "16\u2103", "tianqi": "\u9634~\u9635\u96e8", "fengxiang": "\u5357\u98ce", "fengli": "\u5fae\u98ce", "aqi": "68", "aqiInfo": "\u826f", "aqiLevel": "2"}, {"ymd": "2016-05-28", "bWendu": "25\u2103", "yWendu": "17\u2103", "tianqi": "\u591a\u4e91", "fengxiang": "\u5317\u98ce", "fengli": "\u5fae\u98ce", "aqi": "123", "aqiInfo": "\u8f7b\u5ea6\u6c61\u67d3", "aqiLevel": "3"}, {"ymd": "2016-05-29", "bWendu": "29\u2103", "yWendu": "17\u2103", "tianqi": "\u591a\u4e91", "fengxiang": "\u5357\u98ce", "fengli": "\u5fae\u98ce", "aqi": "92", "aqiInfo": "\u826f", "aqiLevel": "2"}, {"ymd": "2016-05-30", "bWendu": "28\u2103", "yWendu": "20\u2103", "tianqi": "\u5c0f\u96e8", "fengxiang": "\u5357\u98ce", "fengli": "\u5fae\u98ce", "aqi": "104", "aqiInfo": "\u8f7b\u5ea6\u6c61\u67d3", "aqiLevel": "3"}, {"ymd": "2016-05-31", "bWendu": "30\u2103", "yWendu": "21\u2103", "tianqi": "\u5c0f\u96e8~\u9634", "fengxiang": "\u5357\u98ce", "fengli": "\u5fae\u98ce", "aqi": "107", "aqiInfo": "\u8f7b\u5ea6\u6c61\u67d3", "aqiLevel": "3"}]}